pretix_invoice_net/__init__.py
pretix_invoice_net/apps.py
pretix_invoice_net/invoice.py
pretix_invoice_net/signals.py
pretix_invoice_net/locale/de/LC_MESSAGES/django.po
pretix_invoice_net/locale/de_Informal/.gitkeep
pretix_invoice_net/locale/de_Informal/LC_MESSAGES/django.po
pretix_invoice_net/static/pretix_invoice_net/.gitkeep
pretix_invoice_net/templates/pretix_invoice_net/.gitkeep
pretix_invoice_net-1.0.4.dist-info/LICENSE
pretix_invoice_net-1.0.4.dist-info/METADATA
pretix_invoice_net-1.0.4.dist-info/WHEEL
pretix_invoice_net-1.0.4.dist-info/entry_points.txt
pretix_invoice_net-1.0.4.dist-info/top_level.txt
pretix_invoice_net-1.0.4.dist-info/RECORD
