Metadata-Version: 2.1
Name: pretix-invoice-net
Version: 1.0.4
Summary: Pretix invoice renderer plugin for NETWAYS
Home-page: https://github.com/NETWAYS/pretix-invoice-net
Download-URL: https://github.com/NETWAYS/pretix-invoice-net/archive/v1.0.2.tar.gz
Author: NETWAYS GmbH
Author-email: support@netways.de
License: Apache Software License
Keywords: pretix,tickets,events,invoice,pdf
License-File: LICENSE
